zedstat/Untitled-Copy1.ipynb
zedstat/Untitled.ipynb
zedstat/__init__.py
zedstat/ci.py
zedstat/mwauc.py
zedstat/rrci.py
zedstat/textable.py
zedstat/zedstat.py
zedstat/.ipynb_checkpoints/Untitled-Copy1-checkpoint.ipynb
zedstat/.ipynb_checkpoints/Untitled-checkpoint.ipynb
zedstat/.ipynb_checkpoints/example3-checkpoint.ipynb
zedstat-0.0.141.dist-info/LICENSE
zedstat-0.0.141.dist-info/METADATA
zedstat-0.0.141.dist-info/WHEEL
zedstat-0.0.141.dist-info/top_level.txt
zedstat-0.0.141.dist-info/RECORD
