Metadata-Version: 2.1
Name: zedstat
Version: 0.0.141
Summary: Statistics tools for ML models and deployment
Home-page: https://github.com/zeroknowledgediscovery/zedstat
Download-URL: https://github.com/zeroknowledgediscovery/zedstat/archive/0.0.141.tar.gz
Author: zed.uchicago.edu
Author-email: ishanu@uchicago.edu
License: LICENSE
Keywords: machine learning,statistics
Classifier: Development Status :: 4 - Beta
Classifier: Intended Audience :: Developers
Classifier: Intended Audience :: Science/Research
Classifier: Topic :: Scientific/Engineering :: Information Analysis
Classifier: Topic :: Software Development :: Libraries
Classifier: License :: OSI Approved :: MIT License
Classifier: Programming Language :: Python :: 3.6
Requires-Python: >=3.6
License-File: LICENSE
Requires-Dist: scikit-learn
Requires-Dist: scipy
Requires-Dist: numpy
Requires-Dist: pandas
